docs/conf.py
ada_url/_ada_wrapper.abi3.so
ada_url/ada_c.h
ada_url/__init__.py
ada_url/ada.h
ada_url/ada_build.py
ada_url/py.typed
ada_url/ada_adapter.py
ada_url/ada.cpp
ada_url-1.28.0.dist-info/RECORD
ada_url-1.28.0.dist-info/WHEEL
ada_url-1.28.0.dist-info/top_level.txt
ada_url-1.28.0.dist-info/METADATA
ada_url-1.28.0.dist-info/licenses/LICENSE
